pyMR/__init__.py
pyMR/chunk.py
pyMR/main.py
pyMR/utils.py
pyParallelMR-0.1.2.dist-info/LICENSE
pyParallelMR-0.1.2.dist-info/METADATA
pyParallelMR-0.1.2.dist-info/WHEEL
pyParallelMR-0.1.2.dist-info/top_level.txt
pyParallelMR-0.1.2.dist-info/RECORD
