Metadata-Version: 2.1
Name: pyParallelMR
Version: 0.1.2
Summary: A python package to convert CPU-bound tasks to parallel mapReduce jobs.
Home-page: https://github.com/k4rth33k/pyMR
Author: k4rth33k
Author-email: kartheek2000mike@gmail.com
License: MIT
Platform: UNKNOWN
Requires-Python: >=3.2S
